ircbgp/__init__.py
ircbgp/_version.py
ircbgp/bot.py
ircbgp-0.0.1.dist-info/LICENSE
ircbgp-0.0.1.dist-info/METADATA
ircbgp-0.0.1.dist-info/WHEEL
ircbgp-0.0.1.dist-info/entry_points.txt
ircbgp-0.0.1.dist-info/top_level.txt
ircbgp-0.0.1.dist-info/RECORD
