Metadata-Version: 2.1
Name: ircbgp
Version: 0.0.1
Summary: Proof of concept implementation for an IRC bot to simulate bgp with students.
Home-page: https://github.com/mutax/ircbgp
Author: Florian Streibelt
Author-email: pypi@streibelt.net
License: UNKNOWN
Platform: UNKNOWN
Classifier: Programming Language :: Python :: 3
Classifier: License :: OSI Approved :: MIT License
Classifier: Operating System :: OS Independent
Requires-Python: >=3.5
Requires-Dist: irc
Requires-Dist: jaraco
